{"devicePlatform":"","logFolder":"C:\\Users\\M.Kamel\\git\\regression2\\Reports\\advanced search1\\20181204_115444","runData":{"hostName":"M.Kamel - 10.1.210.151","os":"Windows 10 64bit","katalonVersion":"5.7.1.1","browser":"Chrome 70.0.3538.110","hostAddress":"10.1.210.151","sessionId":"3c9034aadf49ce6b628aeac0a1dd1b1e","seleniumVersion":"3.7.1","proxyInformation":"ProxyInformation{proxyOption\u003dNO_PROXY, proxyServerType\u003dHTTP, password\u003d, proxyServerAddress\u003d, proxyServerPort\u003d0}","platform":"Windows 10"},"type":"TEST_SUITE","name":"advanced search1","id":"Test Suites/advanced search1","source":"","message":"Test Cases/Final/search with gender","description":"","startTime":1543917288866,"endTime":1543917410261,"childRecords":[{"isOptional":false,"type":"TEST_CASE","name":"Test Cases/Final/search_with_specialty","id":"Test Cases/Final/search_with_specialty","source":"C:\\\\Users\\\\M.Kamel\\\\git\\\\regression2\\\\Test Cases\\\\Final\\\\search_with_specialty.tc","message":"Test Cases/Final/search_with_specialty","description":"","startTime":1543917289760,"endTime":1543917337629,"childRecords":[{"testStatus":{"stackTrace":"","statusValue":"INFO"},"type":"MESSAGE","name":"","message":"Evaluating variables for test case","startTime":1543917289782,"endTime":0,"childRecords":[],"interuppted":false},{"index":1,"isIgnoredIfFailed":false,"type":"TEST_STEP","name":"openBrowser","message":"Browser is opened with url: \u0027\u0027","description":"","startTime":1543917290029,"endTime":1543917297229,"childRecords":[{"testStatus":{"stackTrace":"","statusValue":"PASSED"},"type":"MESSAGE","name":"","message":"Browser is opened with url: \u0027\u0027","startTime":1543917297228,"endTime":0,"childRecords":[],"interuppted":false}],"interuppted":false},{"index":2,"isIgnoredIfFailed":false,"type":"TEST_STEP","name":"maximizeWindow","message":"Current window maximized","description":"","startTime":1543917297230,"endTime":1543917298557,"childRecords":[{"testStatus":{"stackTrace":"","statusValue":"PASSED"},"type":"MESSAGE","name":"","message":"Current window maximized","startTime":1543917298554,"endTime":0,"childRecords":[],"interuppted":false}],"interuppted":false},{"index":3,"isIgnoredIfFailed":false,"type":"TEST_STEP","name":"navigateToUrl","message":"Navigate to \u0027https://www.schooolz.com\u0027 successfully","description":"","startTime":1543917298559,"endTime":1543917310723,"childRecords":[{"testStatus":{"stackTrace":"","statusValue":"PASSED"},"type":"MESSAGE","name":"","message":"Navigate to \u0027https://www.schooolz.com\u0027 successfully","startTime":1543917310721,"endTime":0,"childRecords":[],"interuppted":false}],"interuppted":false},{"index":4,"isIgnoredIfFailed":false,"type":"TEST_STEP","name":"click","message":"Object: \u0027Object Repository/advanced search1/home_search_btn\u0027 is clicked on","description":"","startTime":1543917310723,"endTime":1543917311818,"childRecords":[{"testStatus":{"stackTrace":"","statusValue":"PASSED"},"type":"MESSAGE","name":"","message":"Object: \u0027Object Repository/advanced search1/home_search_btn\u0027 is clicked on","startTime":1543917311818,"endTime":0,"childRecords":[],"interuppted":false}],"interuppted":false},{"index":5,"isIgnoredIfFailed":false,"type":"TEST_STEP","name":"delay","message":"Delayed 3 second(s)","description":"","startTime":1543917311819,"endTime":1543917314840,"childRecords":[{"testStatus":{"stackTrace":"","statusValue":"PASSED"},"type":"MESSAGE","name":"","message":"Delayed 3 second(s)","startTime":1543917314840,"endTime":0,"childRecords":[],"interuppted":false}],"interuppted":false},{"index":6,"isIgnoredIfFailed":false,"type":"TEST_STEP","name":"click","message":"Object: \u0027Object Repository/advanced search1/advanced_search_btn\u0027 is clicked on","description":"","startTime":1543917314841,"endTime":1543917316368,"childRecords":[{"testStatus":{"stackTrace":"","statusValue":"PASSED"},"type":"MESSAGE","name":"","message":"Object: \u0027Object Repository/advanced search1/advanced_search_btn\u0027 is clicked on","startTime":1543917316367,"endTime":0,"childRecords":[],"interuppted":false}],"interuppted":false},{"index":7,"isIgnoredIfFailed":false,"type":"TEST_STEP","name":"delay","message":"Delayed 3 second(s)","description":"","startTime":1543917316368,"endTime":1543917319369,"childRecords":[{"testStatus":{"stackTrace":"","statusValue":"PASSED"},"type":"MESSAGE","name":"","message":"Delayed 3 second(s)","startTime":1543917319369,"endTime":0,"childRecords":[],"interuppted":false}],"interuppted":false},{"index":8,"isIgnoredIfFailed":false,"type":"TEST_STEP","name":"click","message":"Object: \u0027Object Repository/advanced search1/spciality\u0027 is clicked on","description":"","startTime":1543917319370,"endTime":1543917319450,"childRecords":[{"testStatus":{"stackTrace":"","statusValue":"PASSED"},"type":"MESSAGE","name":"","message":"Object: \u0027Object Repository/advanced search1/spciality\u0027 is clicked on","startTime":1543917319449,"endTime":0,"childRecords":[],"interuppted":false}],"interuppted":false},{"index":9,"isIgnoredIfFailed":false,"type":"TEST_STEP","name":"delay","message":"Delayed 3 second(s)","description":"","startTime":1543917319450,"endTime":1543917322454,"childRecords":[{"testStatus":{"stackTrace":"","statusValue":"PASSED"},"type":"MESSAGE","name":"","message":"Delayed 3 second(s)","startTime":1543917322453,"endTime":0,"childRecords":[],"interuppted":false}],"interuppted":false},{"index":10,"isIgnoredIfFailed":false,"type":"TEST_STEP","name":"check","message":"Object \u0027Object Repository/advanced search1/governmental_checkbox\u0027 is checked","description":"","startTime":1543917322454,"endTime":1543917327575,"childRecords":[{"testStatus":{"stackTrace":"","statusValue":"PASSED"},"type":"MESSAGE","name":"","message":"Object \u0027Object Repository/advanced search1/governmental_checkbox\u0027 is checked","startTime":1543917327574,"endTime":0,"childRecords":[],"interuppted":false}],"interuppted":false},{"index":11,"isIgnoredIfFailed":false,"type":"TEST_STEP","name":"verifyElementChecked","message":"Object \u0027Object Repository/advanced search1/governmental_checkbox\u0027 is checked","description":"","startTime":1543917327575,"endTime":1543917327624,"childRecords":[{"testStatus":{"stackTrace":"","statusValue":"WARNING"},"type":"MESSAGE","name":"","message":"Timeout \u00270\u0027 is invalid. Using default page load timeout: \u002730\u0027","startTime":1543917327591,"endTime":0,"childRecords":[],"interuppted":false},{"testStatus":{"stackTrace":"","statusValue":"PASSED"},"type":"MESSAGE","name":"","message":"Object \u0027Object Repository/advanced search1/governmental_checkbox\u0027 is checked","startTime":1543917327623,"endTime":0,"childRecords":[],"interuppted":false}],"interuppted":false},{"index":12,"isIgnoredIfFailed":false,"type":"TEST_STEP","name":"delay","message":"Delayed 10 second(s)","description":"","startTime":1543917327624,"endTime":1543917337627,"childRecords":[{"testStatus":{"stackTrace":"","statusValue":"PASSED"},"type":"MESSAGE","name":"","message":"Delayed 10 second(s)","startTime":1543917337626,"endTime":0,"childRecords":[],"interuppted":false}],"interuppted":false},{"index":13,"isIgnoredIfFailed":false,"type":"TEST_STEP","name":"verifyTextPresent","message":"NOT_RUN: verifyTextPresent","description":"","startTime":1543917337627,"endTime":1543917337628,"childRecords":[{"testStatus":{"stackTrace":"","statusValue":"NOT_RUN"},"type":"MESSAGE","name":"","message":"NOT_RUN: verifyTextPresent","startTime":1543917337628,"endTime":0,"childRecords":[],"interuppted":false}],"interuppted":false},{"testStatus":{"stackTrace":"","statusValue":"PASSED"},"type":"MESSAGE","name":"","message":"Test Cases/Final/search_with_specialty","startTime":1543917337629,"endTime":0,"childRecords":[],"interuppted":false}],"interuppted":false},{"isOptional":false,"type":"TEST_CASE","name":"Test Cases/Final/search with kind of school","id":"Test Cases/Final/search with kind of school","source":"C:\\\\Users\\\\M.Kamel\\\\git\\\\regression2\\\\Test Cases\\\\Final\\\\search with kind of school.tc","message":"Test Cases/Final/search with kind of school","description":"","startTime":1543917337633,"endTime":1543917360929,"childRecords":[{"testStatus":{"stackTrace":"","statusValue":"INFO"},"type":"MESSAGE","name":"","message":"Evaluating variables for test case","startTime":1543917337659,"endTime":0,"childRecords":[],"interuppted":false},{"index":1,"isIgnoredIfFailed":false,"type":"TEST_STEP","name":"openBrowser","message":"NOT_RUN: openBrowser","description":"","startTime":1543917337784,"endTime":1543917337784,"childRecords":[{"testStatus":{"stackTrace":"","statusValue":"NOT_RUN"},"type":"MESSAGE","name":"","message":"NOT_RUN: openBrowser","startTime":1543917337784,"endTime":0,"childRecords":[],"interuppted":false}],"interuppted":false},{"index":2,"isIgnoredIfFailed":false,"type":"TEST_STEP","name":"maximizeWindow","message":"NOT_RUN: maximizeWindow","description":"","startTime":1543917337785,"endTime":1543917337785,"childRecords":[{"testStatus":{"stackTrace":"","statusValue":"NOT_RUN"},"type":"MESSAGE","name":"","message":"NOT_RUN: maximizeWindow","startTime":1543917337785,"endTime":0,"childRecords":[],"interuppted":false}],"interuppted":false},{"index":3,"isIgnoredIfFailed":false,"type":"TEST_STEP","name":"navigateToUrl","message":"NOT_RUN: navigateToUrl","description":"","startTime":1543917337786,"endTime":1543917337786,"childRecords":[{"testStatus":{"stackTrace":"","statusValue":"NOT_RUN"},"type":"MESSAGE","name":"","message":"NOT_RUN: navigateToUrl","startTime":1543917337786,"endTime":0,"childRecords":[],"interuppted":false}],"interuppted":false},{"index":4,"isIgnoredIfFailed":false,"type":"TEST_STEP","name":"click","message":"NOT_RUN: click","description":"","startTime":1543917337786,"endTime":1543917337787,"childRecords":[{"testStatus":{"stackTrace":"","statusValue":"NOT_RUN"},"type":"MESSAGE","name":"","message":"NOT_RUN: click","startTime":1543917337787,"endTime":0,"childRecords":[],"interuppted":false}],"interuppted":false},{"index":5,"isIgnoredIfFailed":false,"type":"TEST_STEP","name":"delay","message":"NOT_RUN: delay","description":"","startTime":1543917337787,"endTime":1543917337787,"childRecords":[{"testStatus":{"stackTrace":"","statusValue":"NOT_RUN"},"type":"MESSAGE","name":"","message":"NOT_RUN: delay","startTime":1543917337787,"endTime":0,"childRecords":[],"interuppted":false}],"interuppted":false},{"index":6,"isIgnoredIfFailed":false,"type":"TEST_STEP","name":"click","message":"NOT_RUN: click","description":"","startTime":1543917337788,"endTime":1543917337788,"childRecords":[{"testStatus":{"stackTrace":"","statusValue":"NOT_RUN"},"type":"MESSAGE","name":"","message":"NOT_RUN: click","startTime":1543917337788,"endTime":0,"childRecords":[],"interuppted":false}],"interuppted":false},{"index":7,"isIgnoredIfFailed":false,"type":"TEST_STEP","name":"delay","message":"Delayed 3 second(s)","description":"","startTime":1543917337788,"endTime":1543917340790,"childRecords":[{"testStatus":{"stackTrace":"","statusValue":"PASSED"},"type":"MESSAGE","name":"","message":"Delayed 3 second(s)","startTime":1543917340789,"endTime":0,"childRecords":[],"interuppted":false}],"interuppted":false},{"index":8,"isIgnoredIfFailed":false,"type":"TEST_STEP","name":"click","message":"Object: \u0027Object Repository/advanced search1/kind of school\u0027 is clicked on","description":"","startTime":1543917340790,"endTime":1543917342678,"childRecords":[{"testStatus":{"stackTrace":"","statusValue":"PASSED"},"type":"MESSAGE","name":"","message":"Object: \u0027Object Repository/advanced search1/kind of school\u0027 is clicked on","startTime":1543917342677,"endTime":0,"childRecords":[],"interuppted":false}],"interuppted":false},{"index":9,"isIgnoredIfFailed":false,"type":"TEST_STEP","name":"delay","message":"Delayed 3 second(s)","description":"","startTime":1543917342678,"endTime":1543917345679,"childRecords":[{"testStatus":{"stackTrace":"","statusValue":"PASSED"},"type":"MESSAGE","name":"","message":"Delayed 3 second(s)","startTime":1543917345679,"endTime":0,"childRecords":[],"interuppted":false}],"interuppted":false},{"index":10,"isIgnoredIfFailed":false,"type":"TEST_STEP","name":"check","message":"Object \u0027Object Repository/advanced search1/kind_of_school_checkbox\u0027 is checked","description":"","startTime":1543917345679,"endTime":1543917350879,"childRecords":[{"testStatus":{"stackTrace":"","statusValue":"PASSED"},"type":"MESSAGE","name":"","message":"Object \u0027Object Repository/advanced search1/kind_of_school_checkbox\u0027 is checked","startTime":1543917350879,"endTime":0,"childRecords":[],"interuppted":false}],"interuppted":false},{"index":11,"isIgnoredIfFailed":false,"type":"TEST_STEP","name":"verifyElementChecked","message":"Object \u0027Object Repository/advanced search1/kind_of_school_checkbox\u0027 is checked","description":"","startTime":1543917350879,"endTime":1543917350926,"childRecords":[{"testStatus":{"stackTrace":"","statusValue":"WARNING"},"type":"MESSAGE","name":"","message":"Timeout \u00270\u0027 is invalid. Using default page load timeout: \u002730\u0027","startTime":1543917350883,"endTime":0,"childRecords":[],"interuppted":false},{"testStatus":{"stackTrace":"","statusValue":"PASSED"},"type":"MESSAGE","name":"","message":"Object \u0027Object Repository/advanced search1/kind_of_school_checkbox\u0027 is checked","startTime":1543917350925,"endTime":0,"childRecords":[],"interuppted":false}],"interuppted":false},{"index":12,"isIgnoredIfFailed":false,"type":"TEST_STEP","name":"delay","message":"Delayed 10 second(s)","description":"","startTime":1543917350926,"endTime":1543917360928,"childRecords":[{"testStatus":{"stackTrace":"","statusValue":"PASSED"},"type":"MESSAGE","name":"","message":"Delayed 10 second(s)","startTime":1543917360928,"endTime":0,"childRecords":[],"interuppted":false}],"interuppted":false},{"index":13,"isIgnoredIfFailed":false,"type":"TEST_STEP","name":"delay","message":"NOT_RUN: delay","description":"","startTime":1543917360928,"endTime":1543917360929,"childRecords":[{"testStatus":{"stackTrace":"","statusValue":"NOT_RUN"},"type":"MESSAGE","name":"","message":"NOT_RUN: delay","startTime":1543917360929,"endTime":0,"childRecords":[],"interuppted":false}],"interuppted":false},{"testStatus":{"stackTrace":"","statusValue":"PASSED"},"type":"MESSAGE","name":"","message":"Test Cases/Final/search with kind of school","startTime":1543917360929,"endTime":0,"childRecords":[],"interuppted":false}],"interuppted":false},{"isOptional":false,"type":"TEST_CASE","name":"Test Cases/Final/search with country","id":"Test Cases/Final/search with country","source":"C:\\\\Users\\\\M.Kamel\\\\git\\\\regression2\\\\Test Cases\\\\Final\\\\search with country.tc","message":"Test Cases/Final/search with country","description":"","startTime":1543917360932,"endTime":1543917373804,"childRecords":[{"testStatus":{"stackTrace":"","statusValue":"INFO"},"type":"MESSAGE","name":"","message":"Evaluating variables for test case","startTime":1543917360939,"endTime":0,"childRecords":[],"interuppted":false},{"index":1,"isIgnoredIfFailed":false,"type":"TEST_STEP","name":"openBrowser","message":"NOT_RUN: openBrowser","description":"","startTime":1543917361052,"endTime":1543917361053,"childRecords":[{"testStatus":{"stackTrace":"","statusValue":"NOT_RUN"},"type":"MESSAGE","name":"","message":"NOT_RUN: openBrowser","startTime":1543917361052,"endTime":0,"childRecords":[],"interuppted":false}],"interuppted":false},{"index":2,"isIgnoredIfFailed":false,"type":"TEST_STEP","name":"maximizeWindow","message":"NOT_RUN: maximizeWindow","description":"","startTime":1543917361053,"endTime":1543917361053,"childRecords":[{"testStatus":{"stackTrace":"","statusValue":"NOT_RUN"},"type":"MESSAGE","name":"","message":"NOT_RUN: maximizeWindow","startTime":1543917361053,"endTime":0,"childRecords":[],"interuppted":false}],"interuppted":false},{"index":3,"isIgnoredIfFailed":false,"type":"TEST_STEP","name":"navigateToUrl","message":"NOT_RUN: navigateToUrl","description":"","startTime":1543917361054,"endTime":1543917361054,"childRecords":[{"testStatus":{"stackTrace":"","statusValue":"NOT_RUN"},"type":"MESSAGE","name":"","message":"NOT_RUN: navigateToUrl","startTime":1543917361054,"endTime":0,"childRecords":[],"interuppted":false}],"interuppted":false},{"index":4,"isIgnoredIfFailed":false,"type":"TEST_STEP","name":"click","message":"NOT_RUN: click","description":"","startTime":1543917361054,"endTime":1543917361055,"childRecords":[{"testStatus":{"stackTrace":"","statusValue":"NOT_RUN"},"type":"MESSAGE","name":"","message":"NOT_RUN: click","startTime":1543917361055,"endTime":0,"childRecords":[],"interuppted":false}],"interuppted":false},{"index":5,"isIgnoredIfFailed":false,"type":"TEST_STEP","name":"delay","message":"NOT_RUN: delay","description":"","startTime":1543917361055,"endTime":1543917361056,"childRecords":[{"testStatus":{"stackTrace":"","statusValue":"NOT_RUN"},"type":"MESSAGE","name":"","message":"NOT_RUN: delay","startTime":1543917361055,"endTime":0,"childRecords":[],"interuppted":false}],"interuppted":false},{"index":6,"isIgnoredIfFailed":false,"type":"TEST_STEP","name":"click","message":"NOT_RUN: click","description":"","startTime":1543917361056,"endTime":1543917361056,"childRecords":[{"testStatus":{"stackTrace":"","statusValue":"NOT_RUN"},"type":"MESSAGE","name":"","message":"NOT_RUN: click","startTime":1543917361056,"endTime":0,"childRecords":[],"interuppted":false}],"interuppted":false},{"index":7,"isIgnoredIfFailed":false,"type":"TEST_STEP","name":"delay","message":"Delayed 3 second(s)","description":"","startTime":1543917361057,"endTime":1543917364059,"childRecords":[{"testStatus":{"stackTrace":"","statusValue":"PASSED"},"type":"MESSAGE","name":"","message":"Delayed 3 second(s)","startTime":1543917364058,"endTime":0,"childRecords":[],"interuppted":false}],"interuppted":false},{"index":8,"isIgnoredIfFailed":false,"type":"TEST_STEP","name":"click","message":"Object: \u0027Object Repository/advanced search1/country\u0027 is clicked on","description":"","startTime":1543917364059,"endTime":1543917369485,"childRecords":[{"testStatus":{"stackTrace":"","statusValue":"PASSED"},"type":"MESSAGE","name":"","message":"Object: \u0027Object Repository/advanced search1/country\u0027 is clicked on","startTime":1543917369484,"endTime":0,"childRecords":[],"interuppted":false}],"interuppted":false},{"index":9,"isIgnoredIfFailed":false,"type":"TEST_STEP","name":"delay","message":"Delayed 3 second(s)","description":"","startTime":1543917369485,"endTime":1543917372487,"childRecords":[{"testStatus":{"stackTrace":"","statusValue":"PASSED"},"type":"MESSAGE","name":"","message":"Delayed 3 second(s)","startTime":1543917372486,"endTime":0,"childRecords":[],"interuppted":false}],"interuppted":false},{"index":10,"isIgnoredIfFailed":false,"type":"TEST_STEP","name":"check","message":"Object \u0027Object Repository/advanced search1/country_checkbox\u0027 is checked","description":"","startTime":1543917372487,"endTime":1543917372770,"childRecords":[{"testStatus":{"stackTrace":"","statusValue":"PASSED"},"type":"MESSAGE","name":"","message":"Object \u0027Object Repository/advanced search1/country_checkbox\u0027 is checked","startTime":1543917372770,"endTime":0,"childRecords":[],"interuppted":false}],"interuppted":false},{"index":11,"isIgnoredIfFailed":false,"type":"TEST_STEP","name":"verifyElementChecked","message":"Object \u0027Object Repository/advanced search1/country_checkbox\u0027 is checked","description":"","startTime":1543917372770,"endTime":1543917372803,"childRecords":[{"testStatus":{"stackTrace":"","statusValue":"WARNING"},"type":"MESSAGE","name":"","message":"Timeout \u00270\u0027 is invalid. Using default page load timeout: \u002730\u0027","startTime":1543917372773,"endTime":0,"childRecords":[],"interuppted":false},{"testStatus":{"stackTrace":"","statusValue":"PASSED"},"type":"MESSAGE","name":"","message":"Object \u0027Object Repository/advanced search1/country_checkbox\u0027 is checked","startTime":1543917372802,"endTime":0,"childRecords":[],"interuppted":false}],"interuppted":false},{"index":12,"isIgnoredIfFailed":false,"type":"TEST_STEP","name":"delay","message":"Delayed 1 second(s)","description":"","startTime":1543917372803,"endTime":1543917373804,"childRecords":[{"testStatus":{"stackTrace":"","statusValue":"PASSED"},"type":"MESSAGE","name":"","message":"Delayed 1 second(s)","startTime":1543917373804,"endTime":0,"childRecords":[],"interuppted":false}],"interuppted":false},{"testStatus":{"stackTrace":"","statusValue":"PASSED"},"type":"MESSAGE","name":"","message":"Test Cases/Final/search with country","startTime":1543917373804,"endTime":0,"childRecords":[],"interuppted":false}],"interuppted":false},{"isOptional":false,"type":"TEST_CASE","name":"Test Cases/Final/search with city","id":"Test Cases/Final/search with city","source":"C:\\\\Users\\\\M.Kamel\\\\git\\\\regression2\\\\Test Cases\\\\Final\\\\search with city.tc","message":"Test Cases/Final/search with city","description":"","startTime":1543917373807,"endTime":1543917390537,"childRecords":[{"testStatus":{"stackTrace":"","statusValue":"INFO"},"type":"MESSAGE","name":"","message":"Evaluating variables for test case","startTime":1543917373814,"endTime":0,"childRecords":[],"interuppted":false},{"index":1,"isIgnoredIfFailed":false,"type":"TEST_STEP","name":"openBrowser","message":"NOT_RUN: openBrowser","description":"","startTime":1543917374197,"endTime":1543917374198,"childRecords":[{"testStatus":{"stackTrace":"","statusValue":"NOT_RUN"},"type":"MESSAGE","name":"","message":"NOT_RUN: openBrowser","startTime":1543917374198,"endTime":0,"childRecords":[],"interuppted":false}],"interuppted":false},{"index":2,"isIgnoredIfFailed":false,"type":"TEST_STEP","name":"maximizeWindow","message":"NOT_RUN: maximizeWindow","description":"","startTime":1543917374198,"endTime":1543917374199,"childRecords":[{"testStatus":{"stackTrace":"","statusValue":"NOT_RUN"},"type":"MESSAGE","name":"","message":"NOT_RUN: maximizeWindow","startTime":1543917374199,"endTime":0,"childRecords":[],"interuppted":false}],"interuppted":false},{"index":3,"isIgnoredIfFailed":false,"type":"TEST_STEP","name":"navigateToUrl","message":"NOT_RUN: navigateToUrl","description":"","startTime":1543917374199,"endTime":1543917374200,"childRecords":[{"testStatus":{"stackTrace":"","statusValue":"NOT_RUN"},"type":"MESSAGE","name":"","message":"NOT_RUN: navigateToUrl","startTime":1543917374200,"endTime":0,"childRecords":[],"interuppted":false}],"interuppted":false},{"index":4,"isIgnoredIfFailed":false,"type":"TEST_STEP","name":"click","message":"NOT_RUN: click","description":"","startTime":1543917374200,"endTime":1543917374200,"childRecords":[{"testStatus":{"stackTrace":"","statusValue":"NOT_RUN"},"type":"MESSAGE","name":"","message":"NOT_RUN: click","startTime":1543917374200,"endTime":0,"childRecords":[],"interuppted":false}],"interuppted":false},{"index":5,"isIgnoredIfFailed":false,"type":"TEST_STEP","name":"delay","message":"NOT_RUN: delay","description":"","startTime":1543917374200,"endTime":1543917374201,"childRecords":[{"testStatus":{"stackTrace":"","statusValue":"NOT_RUN"},"type":"MESSAGE","name":"","message":"NOT_RUN: delay","startTime":1543917374201,"endTime":0,"childRecords":[],"interuppted":false}],"interuppted":false},{"index":6,"isIgnoredIfFailed":false,"type":"TEST_STEP","name":"click","message":"NOT_RUN: click","description":"","startTime":1543917374201,"endTime":1543917374201,"childRecords":[{"testStatus":{"stackTrace":"","statusValue":"NOT_RUN"},"type":"MESSAGE","name":"","message":"NOT_RUN: click","startTime":1543917374201,"endTime":0,"childRecords":[],"interuppted":false}],"interuppted":false},{"index":7,"isIgnoredIfFailed":false,"type":"TEST_STEP","name":"delay","message":"NOT_RUN: delay","description":"","startTime":1543917374201,"endTime":1543917374202,"childRecords":[{"testStatus":{"stackTrace":"","statusValue":"NOT_RUN"},"type":"MESSAGE","name":"","message":"NOT_RUN: delay","startTime":1543917374202,"endTime":0,"childRecords":[],"interuppted":false}],"interuppted":false},{"index":8,"isIgnoredIfFailed":false,"type":"TEST_STEP","name":"click","message":"NOT_RUN: click","description":"","startTime":1543917374202,"endTime":1543917374203,"childRecords":[{"testStatus":{"stackTrace":"","statusValue":"NOT_RUN"},"type":"MESSAGE","name":"","message":"NOT_RUN: click","startTime":1543917374202,"endTime":0,"childRecords":[],"interuppted":false}],"interuppted":false},{"index":9,"isIgnoredIfFailed":false,"type":"TEST_STEP","name":"delay","message":"NOT_RUN: delay","description":"","startTime":1543917374203,"endTime":1543917374203,"childRecords":[{"testStatus":{"stackTrace":"","statusValue":"NOT_RUN"},"type":"MESSAGE","name":"","message":"NOT_RUN: delay","startTime":1543917374203,"endTime":0,"childRecords":[],"interuppted":false}],"interuppted":false},{"index":10,"isIgnoredIfFailed":false,"type":"TEST_STEP","name":"check","message":"NOT_RUN: check","description":"","startTime":1543917374203,"endTime":1543917374204,"childRecords":[{"testStatus":{"stackTrace":"","statusValue":"NOT_RUN"},"type":"MESSAGE","name":"","message":"NOT_RUN: check","startTime":1543917374203,"endTime":0,"childRecords":[],"interuppted":false}],"interuppted":false},{"index":11,"isIgnoredIfFailed":false,"type":"TEST_STEP","name":"verifyElementChecked","message":"NOT_RUN: verifyElementChecked","description":"","startTime":1543917374204,"endTime":1543917374204,"childRecords":[{"testStatus":{"stackTrace":"","statusValue":"NOT_RUN"},"type":"MESSAGE","name":"","message":"NOT_RUN: verifyElementChecked","startTime":1543917374204,"endTime":0,"childRecords":[],"interuppted":false}],"interuppted":false},{"index":12,"isIgnoredIfFailed":false,"type":"TEST_STEP","name":"delay","message":"Delayed 3 second(s)","description":"","startTime":1543917374204,"endTime":1543917377206,"childRecords":[{"testStatus":{"stackTrace":"","statusValue":"PASSED"},"type":"MESSAGE","name":"","message":"Delayed 3 second(s)","startTime":1543917377205,"endTime":0,"childRecords":[],"interuppted":false}],"interuppted":false},{"index":13,"isIgnoredIfFailed":false,"type":"TEST_STEP","name":"click","message":"Object: \u0027Object Repository/advanced search1/city\u0027 is clicked on","description":"","startTime":1543917377206,"endTime":1543917377330,"childRecords":[{"testStatus":{"stackTrace":"","statusValue":"PASSED"},"type":"MESSAGE","name":"","message":"Object: \u0027Object Repository/advanced search1/city\u0027 is clicked on","startTime":1543917377329,"endTime":0,"childRecords":[],"interuppted":false}],"interuppted":false},{"index":14,"isIgnoredIfFailed":false,"type":"TEST_STEP","name":"delay","message":"Delayed 3 second(s)","description":"","startTime":1543917377330,"endTime":1543917380332,"childRecords":[{"testStatus":{"stackTrace":"","statusValue":"PASSED"},"type":"MESSAGE","name":"","message":"Delayed 3 second(s)","startTime":1543917380332,"endTime":0,"childRecords":[],"interuppted":false}],"interuppted":false},{"index":15,"isIgnoredIfFailed":false,"type":"TEST_STEP","name":"check","message":"Object \u0027Object Repository/advanced search1/city_checkbox\u0027 is checked","description":"","startTime":1543917380332,"endTime":1543917380497,"childRecords":[{"testStatus":{"stackTrace":"","statusValue":"PASSED"},"type":"MESSAGE","name":"","message":"Object \u0027Object Repository/advanced search1/city_checkbox\u0027 is checked","startTime":1543917380496,"endTime":0,"childRecords":[],"interuppted":false}],"interuppted":false},{"index":16,"isIgnoredIfFailed":false,"type":"TEST_STEP","name":"verifyElementChecked","message":"Object \u0027Object Repository/advanced search1/city_checkbox\u0027 is checked","description":"","startTime":1543917380497,"endTime":1543917380535,"childRecords":[{"testStatus":{"stackTrace":"","statusValue":"WARNING"},"type":"MESSAGE","name":"","message":"Timeout \u00270\u0027 is invalid. Using default page load timeout: \u002730\u0027","startTime":1543917380501,"endTime":0,"childRecords":[],"interuppted":false},{"testStatus":{"stackTrace":"","statusValue":"PASSED"},"type":"MESSAGE","name":"","message":"Object \u0027Object Repository/advanced search1/city_checkbox\u0027 is checked","startTime":1543917380534,"endTime":0,"childRecords":[],"interuppted":false}],"interuppted":false},{"index":17,"isIgnoredIfFailed":false,"type":"TEST_STEP","name":"delay","message":"Delayed 10 second(s)","description":"","startTime":1543917380535,"endTime":1543917390537,"childRecords":[{"testStatus":{"stackTrace":"","statusValue":"PASSED"},"type":"MESSAGE","name":"","message":"Delayed 10 second(s)","startTime":1543917390537,"endTime":0,"childRecords":[],"interuppted":false}],"interuppted":false},{"testStatus":{"stackTrace":"","statusValue":"PASSED"},"type":"MESSAGE","name":"","message":"Test Cases/Final/search with city","startTime":1543917390537,"endTime":0,"childRecords":[],"interuppted":false}],"interuppted":false},{"isOptional":false,"type":"TEST_CASE","name":"Test Cases/Final/search with gender","id":"Test Cases/Final/search with gender","source":"C:\\\\Users\\\\M.Kamel\\\\git\\\\regression2\\\\Test Cases\\\\Final\\\\search with gender.tc","message":"Test Cases/Final/search with gender","description":"","startTime":1543917390540,"endTime":1543917407134,"childRecords":[{"testStatus":{"stackTrace":"","statusValue":"INFO"},"type":"MESSAGE","name":"","message":"Evaluating variables for test case","startTime":1543917390545,"endTime":0,"childRecords":[],"interuppted":false},{"index":1,"isIgnoredIfFailed":false,"type":"TEST_STEP","name":"openBrowser","message":"NOT_RUN: openBrowser","description":"","startTime":1543917390660,"endTime":1543917390660,"childRecords":[{"testStatus":{"stackTrace":"","statusValue":"NOT_RUN"},"type":"MESSAGE","name":"","message":"NOT_RUN: openBrowser","startTime":1543917390660,"endTime":0,"childRecords":[],"interuppted":false}],"interuppted":false},{"index":2,"isIgnoredIfFailed":false,"type":"TEST_STEP","name":"maximizeWindow","message":"NOT_RUN: maximizeWindow","description":"","startTime":1543917390660,"endTime":1543917390661,"childRecords":[{"testStatus":{"stackTrace":"","statusValue":"NOT_RUN"},"type":"MESSAGE","name":"","message":"NOT_RUN: maximizeWindow","startTime":1543917390661,"endTime":0,"childRecords":[],"interuppted":false}],"interuppted":false},{"index":3,"isIgnoredIfFailed":false,"type":"TEST_STEP","name":"navigateToUrl","message":"NOT_RUN: navigateToUrl","description":"","startTime":1543917390661,"endTime":1543917390661,"childRecords":[{"testStatus":{"stackTrace":"","statusValue":"NOT_RUN"},"type":"MESSAGE","name":"","message":"NOT_RUN: navigateToUrl","startTime":1543917390661,"endTime":0,"childRecords":[],"interuppted":false}],"interuppted":false},{"index":4,"isIgnoredIfFailed":false,"type":"TEST_STEP","name":"click","message":"NOT_RUN: click","description":"","startTime":1543917390661,"endTime":1543917390662,"childRecords":[{"testStatus":{"stackTrace":"","statusValue":"NOT_RUN"},"type":"MESSAGE","name":"","message":"NOT_RUN: click","startTime":1543917390662,"endTime":0,"childRecords":[],"interuppted":false}],"interuppted":false},{"index":5,"isIgnoredIfFailed":false,"type":"TEST_STEP","name":"delay","message":"NOT_RUN: delay","description":"","startTime":1543917390662,"endTime":1543917390662,"childRecords":[{"testStatus":{"stackTrace":"","statusValue":"NOT_RUN"},"type":"MESSAGE","name":"","message":"NOT_RUN: delay","startTime":1543917390662,"endTime":0,"childRecords":[],"interuppted":false}],"interuppted":false},{"index":6,"isIgnoredIfFailed":false,"type":"TEST_STEP","name":"click","message":"NOT_RUN: click","description":"","startTime":1543917390662,"endTime":1543917390663,"childRecords":[{"testStatus":{"stackTrace":"","statusValue":"NOT_RUN"},"type":"MESSAGE","name":"","message":"NOT_RUN: click","startTime":1543917390663,"endTime":0,"childRecords":[],"interuppted":false}],"interuppted":false},{"index":7,"isIgnoredIfFailed":false,"type":"TEST_STEP","name":"delay","message":"Delayed 3 second(s)","description":"","startTime":1543917390663,"endTime":1543917393664,"childRecords":[{"testStatus":{"stackTrace":"","statusValue":"PASSED"},"type":"MESSAGE","name":"","message":"Delayed 3 second(s)","startTime":1543917393664,"endTime":0,"childRecords":[],"interuppted":false}],"interuppted":false},{"index":8,"isIgnoredIfFailed":false,"type":"TEST_STEP","name":"click","message":"Object: \u0027Object Repository/advanced search1/gender\u0027 is clicked on","description":"","startTime":1543917393664,"endTime":1543917393901,"childRecords":[{"testStatus":{"stackTrace":"","statusValue":"PASSED"},"type":"MESSAGE","name":"","message":"Object: \u0027Object Repository/advanced search1/gender\u0027 is clicked on","startTime":1543917393901,"endTime":0,"childRecords":[],"interuppted":false}],"interuppted":false},{"index":9,"isIgnoredIfFailed":false,"type":"TEST_STEP","name":"delay","message":"Delayed 3 second(s)","description":"","startTime":1543917393901,"endTime":1543917396903,"childRecords":[{"testStatus":{"stackTrace":"","statusValue":"PASSED"},"type":"MESSAGE","name":"","message":"Delayed 3 second(s)","startTime":1543917396903,"endTime":0,"childRecords":[],"interuppted":false}],"interuppted":false},{"index":10,"isIgnoredIfFailed":false,"type":"TEST_STEP","name":"check","message":"Object \u0027Object Repository/advanced search1/gender1_checkbox\u0027 is checked","description":"","startTime":1543917396904,"endTime":1543917397099,"childRecords":[{"testStatus":{"stackTrace":"","statusValue":"PASSED"},"type":"MESSAGE","name":"","message":"Object \u0027Object Repository/advanced search1/gender1_checkbox\u0027 is checked","startTime":1543917397099,"endTime":0,"childRecords":[],"interuppted":false}],"interuppted":false},{"index":11,"isIgnoredIfFailed":false,"type":"TEST_STEP","name":"verifyElementChecked","message":"Object \u0027Object Repository/advanced search1/gender1_checkbox\u0027 is checked","description":"","startTime":1543917397099,"endTime":1543917397132,"childRecords":[{"testStatus":{"stackTrace":"","statusValue":"WARNING"},"type":"MESSAGE","name":"","message":"Timeout \u00270\u0027 is invalid. Using default page load timeout: \u002730\u0027","startTime":1543917397104,"endTime":0,"childRecords":[],"interuppted":false},{"testStatus":{"stackTrace":"","statusValue":"PASSED"},"type":"MESSAGE","name":"","message":"Object \u0027Object Repository/advanced search1/gender1_checkbox\u0027 is checked","startTime":1543917397132,"endTime":0,"childRecords":[],"interuppted":false}],"interuppted":false},{"index":12,"isIgnoredIfFailed":false,"type":"TEST_STEP","name":"delay","message":"Delayed 10 second(s)","description":"","startTime":1543917397132,"endTime":1543917407133,"childRecords":[{"testStatus":{"stackTrace":"","statusValue":"PASSED"},"type":"MESSAGE","name":"","message":"Delayed 10 second(s)","startTime":1543917407133,"endTime":0,"childRecords":[],"interuppted":false}],"interuppted":false},{"testStatus":{"stackTrace":"","statusValue":"PASSED"},"type":"MESSAGE","name":"","message":"Test Cases/Final/search with gender","startTime":1543917407133,"endTime":0,"childRecords":[],"interuppted":false}],"interuppted":false}],"interuppted":false}